Metadata-Version: 2.1
Name: fsutil
Version: 0.0.5
Summary: This is a file system utilities package.
Home-page: UNKNOWN
Author: Yaniv Avrahami
Author-email: avrahamiyaniv@gmail.com
License: UNKNOWN
Keywords: fsutil
Platform: UNKNOWN
